{
  "description": "Full-history BTCUSDT 1m Prophet walk-forward baseline. Fits each split on the whole historical window before the last-week holdout, so this can be extremely slow.",
  "init_schema": false,
  "symbol": "BTCUSDT",
  "interval": "1m",
  "model_name": "prophet",
  "model_parameters": {
    "daily_seasonality": true,
    "weekly_seasonality": true,
    "yearly_seasonality": true
  },
  "target_field": "close",
  "window_size": 2634000,
  "forecast_horizon": 15,
  "start_time": "2021-05-26T00:00:00Z",
  "end_time": "2026-06-05T22:32:00Z",
  "validation_size": 1,
  "step_size": 1440,
  "required_features": [],
  "artifacts_dir": "experiments/results",
  "backtest": {
    "enabled": true,
    "starting_cash": 10000,
    "buy_threshold": 0.0002
  }
}
